setup.cfg
setup.py
OHM.egg-info/PKG-INFO
OHM.egg-info/SOURCES.txt
OHM.egg-info/dependency_links.txt
OHM.egg-info/not-zip-safe
OHM.egg-info/paster_plugins.txt
OHM.egg-info/requires.txt
OHM.egg-info/top_level.txt
docs/client.txt
docs/index.txt
docs/license.txt
docs/server.txt
docs/todo.txt
ohm/__init__.py
ohm/client.py
ohm/descriptors.py
ohm/lildav.py
ohm/persist.py
ohm/server.py
ohm/validators.py
tests/conftest.py
tests/test_client.py
tests/test_lildav.py
tests/test_persist.py
tests/test_server.py
tests/test_server_full.py
tests/test_xmlrpc.py
