Metadata-Version: 1.0
Name: OHM
Version: 0.1
Summary: Object HTTP Mapper
Home-page: http://pythonpaste.org/ohm/
Author: Ian Bicking
Author-email: ianb@colorstudy.com
License: MIT
Keywords: wsgi web http metaprogramming
Platform: UNKNOWN
Classifier: Development Status :: 3 - Alpha
Classifier: Intended Audience :: Developers
Classifier: License :: OSI Approved :: MIT License
Classifier: Topic :: Internet :: WWW/HTTP
Classifier: Topic :: Internet :: WWW/HTTP :: WSGI
Classifier: Topic :: Internet :: WWW/HTTP :: WSGI :: Application
